pj_robotnotifier/__init__.py
pj_robotnotifier/pj_robotnotifier.py
pj_robotnotifier-0.0.1.dist-info/METADATA
pj_robotnotifier-0.0.1.dist-info/WHEEL
pj_robotnotifier-0.0.1.dist-info/top_level.txt
pj_robotnotifier-0.0.1.dist-info/RECORD
