Metadata-Version: 2.1
Name: pj-robotnotifier
Version: 0.0.1
Summary: Send notifications to Slack or Mattermost using Robot Framework Listener..
Home-page: https://github.com/
Author: PJ Gevana
Author-email: patdroidz@gmail.com
License: MIT
Platform: UNKNOWN
Classifier: License :: OSI Approved :: MIT License
Classifier: Programming Language :: Python :: 3
Classifier: Programming Language :: Python :: 3.6
Classifier: Programming Language :: Python :: 3.7
Classifier: Programming Language :: Python :: 3.8
